connect_db/__init__.py
connect_db/con_db.py
connect_db-0.0.1.dist-info/METADATA
connect_db-0.0.1.dist-info/WHEEL
connect_db-0.0.1.dist-info/top_level.txt
connect_db-0.0.1.dist-info/RECORD
