Metadata-Version: 2.1
Name: connect-db
Version: 0.0.1
Summary: 简化连接数据库操作
Home-page: https://gitee.com
Author: ccb
Author-email: 1278264290@qq.com
License: UNKNOWN
Platform: UNKNOWN
Classifier: Programming Language :: Python :: 3
Classifier: License :: OSI Approved :: MIT License
Classifier: Operating System :: OS Independent
